LICENSE
README.md
pyproject.toml
setup.cfg
setup.py
lavamystic/__init__.py
lavamystic/enums.py
lavamystic/exceptions.py
lavamystic/filters.py
lavamystic/lfu.py
lavamystic/node.py
lavamystic/payloads.py
lavamystic/player.py
lavamystic/py.typed
lavamystic/queue.py
lavamystic/tracks.py
lavamystic/websocket.py
lavamystic.egg-info/PKG-INFO
lavamystic.egg-info/SOURCES.txt
lavamystic.egg-info/dependency_links.txt
lavamystic.egg-info/not-zip-safe
lavamystic.egg-info/requires.txt
lavamystic.egg-info/top_level.txt
lavamystic/types/__init__.py
lavamystic/types/filters.py
lavamystic/types/request.py
lavamystic/types/response.py
lavamystic/types/state.py
lavamystic/types/stats.py
lavamystic/types/tracks.py
lavamystic/types/websocket.py
lavamystic/utils/__init__.py
lavamystic/utils/classproperty.py
lavamystic/utils/namespace.py
lavamystic/utils/decode/__init__.py
lavamystic/utils/decode/dotaio.py
lavamystic/utils/decode/utfm_codec.py