Metadata-Version: 2.1
Name: lavamystic
Version: 1.0.0
Summary: A robust and powerful, fully asynchronous Lavalink wrapper built for disnake in Python.
Author-email: "PythonistaGuild, EvieePy, Krista" <contactchisato@gmail.com>
Project-URL: Homepage, https://github.com/Krispeckt/LavaMystic
Classifier: License :: OSI Approved :: MIT License
Classifier: Intended Audience :: Developers
Classifier: Natural Language :: English
Classifier: Operating System :: OS Independent
Classifier: Programming Language :: Python :: 3.11
Classifier: Programming Language :: Python :: 3.12
Classifier: Topic :: Internet
Classifier: Topic :: Software Development :: Libraries
Classifier: Topic :: Software Development :: Libraries :: Python Modules
Classifier: Topic :: Utilities
Requires-Python: >=3.11
License-File: LICENSE
